package com.tencent.mm.at;

final class e
  implements Runnable
{
  e(d paramd, h paramh)
  {
  }

  // ERROR //
  public final void run()
  {
    // Byte code:
    //   0: invokestatic 29	android/os/Debug:stopMethodTracing	()V
    //   3: aload_0
    //   4: getfield 16	com/tencent/mm/at/e:iHE	Lcom/tencent/mm/at/h;
    //   7: getfield 35	com/tencent/mm/at/h:iHI	Ljava/lang/String;
    //   10: astore 6
    //   12: aload_0
    //   13: getfield 16	com/tencent/mm/at/e:iHE	Lcom/tencent/mm/at/h;
    //   16: getfield 39	com/tencent/mm/at/h:iHH	I
    //   19: istore 7
    //   21: aload_0
    //   22: getfield 16	com/tencent/mm/at/e:iHE	Lcom/tencent/mm/at/h;
    //   25: getfield 35	com/tencent/mm/at/h:iHI	Ljava/lang/String;
    //   28: astore 8
    //   30: aload 8
    //   32: ifnonnull +12 -> 44
    //   35: aload_0
    //   36: getfield 14	com/tencent/mm/at/e:iHF	Lcom/tencent/mm/at/d;
    //   39: invokestatic 45	com/tencent/mm/at/d:b	(Lcom/tencent/mm/at/d;)Z
    //   42: pop
    //   43: return
    //   44: new 47	java/io/File
    //   47: dup
    //   48: aload 6
    //   50: invokespecial 50	java/io/File:<init>	(Ljava/lang/String;)V
    //   53: astore 9
    //   55: new 47	java/io/File
    //   58: dup
    //   59: new 52	java/lang/StringBuilder
    //   62: dup
    //   63: invokespecial 53	java/lang/StringBuilder:<init>	()V
    //   66: aload 6
    //   68: iconst_0
    //   69: aload 6
    //   71: bipush 46
    //   73: invokevirtual 59	java/lang/String:lastIndexOf	(I)I
    //   76: invokevirtual 63	java/lang/String:substring	(II)Ljava/lang/String;
    //   79: invokevirtual 67	java/lang/StringBuilder:append	(Ljava/lang/String;)Ljava/lang/StringBuilder;
    //   82: ldc 69
    //   84: invokevirtual 67	java/lang/StringBuilder:append	(Ljava/lang/String;)Ljava/lang/StringBuilder;
    //   87: invokevirtual 73	java/lang/StringBuilder:toString	()Ljava/lang/String;
    //   90: invokespecial 50	java/io/File:<init>	(Ljava/lang/String;)V
    //   93: astore 10
    //   95: invokestatic 79	java/lang/System:currentTimeMillis	()J
    //   98: lstore 11
    //   100: aload 9
    //   102: aload 10
    //   104: invokevirtual 83	java/io/File:renameTo	(Ljava/io/File;)Z
    //   107: pop
    //   108: aload 9
    //   110: invokevirtual 87	java/io/File:delete	()Z
    //   113: pop
    //   114: ldc 89
    //   116: new 52	java/lang/StringBuilder
    //   119: dup
    //   120: ldc 91
    //   122: invokespecial 92	java/lang/StringBuilder:<init>	(Ljava/lang/String;)V
    //   125: invokestatic 79	java/lang/System:currentTimeMillis	()J
    //   128: lload 11
    //   130: lsub
    //   131: invokevirtual 95	java/lang/StringBuilder:append	(J)Ljava/lang/StringBuilder;
    //   134: invokevirtual 73	java/lang/StringBuilder:toString	()Ljava/lang/String;
    //   137: invokestatic 101	com/tencent/mm/sdk/platformtools/z:i	(Ljava/lang/String;Ljava/lang/String;)V
    //   140: bipush 10
    //   142: invokestatic 107	android/os/Process:setThreadPriority	(I)V
    //   145: aload_0
    //   146: getfield 16	com/tencent/mm/at/e:iHE	Lcom/tencent/mm/at/h;
    //   149: getfield 110	com/tencent/mm/at/h:cOR	I
    //   152: bipush 6
    //   154: if_icmpne +20 -> 174
    //   157: getstatic 114	com/tencent/mm/at/d:jzh	Lcom/tencent/mm/sdk/platformtools/cm;
    //   160: iconst_1
    //   161: invokevirtual 120	com/tencent/mm/sdk/platformtools/cm:sendEmptyMessage	(I)Z
    //   164: pop
    //   165: aload_0
    //   166: getfield 14	com/tencent/mm/at/e:iHF	Lcom/tencent/mm/at/d;
    //   169: invokestatic 45	com/tencent/mm/at/d:b	(Lcom/tencent/mm/at/d;)Z
    //   172: pop
    //   173: return
    //   174: aload_0
    //   175: getfield 14	com/tencent/mm/at/e:iHF	Lcom/tencent/mm/at/d;
    //   178: invokestatic 124	com/tencent/mm/at/d:a	(Lcom/tencent/mm/at/d;)Ljava/util/concurrent/LinkedBlockingQueue;
    //   181: ifnull +16 -> 197
    //   184: aload_0
    //   185: getfield 14	com/tencent/mm/at/e:iHF	Lcom/tencent/mm/at/d;
    //   188: invokestatic 124	com/tencent/mm/at/d:a	(Lcom/tencent/mm/at/d;)Ljava/util/concurrent/LinkedBlockingQueue;
    //   191: invokevirtual 130	java/util/concurrent/LinkedBlockingQueue:size	()I
    //   194: ifne +34 -> 228
    //   197: aload_0
    //   198: getfield 14	com/tencent/mm/at/e:iHF	Lcom/tencent/mm/at/d;
    //   201: pop
    //   202: aload 10
    //   204: invokestatic 134	com/tencent/mm/at/d:m	(Ljava/io/File;)Ljava/lang/String;
    //   207: astore 16
    //   209: aload 16
    //   211: invokestatic 140	com/tencent/mm/sdk/platformtools/ch:jb	(Ljava/lang/String;)Z
    //   214: ifne +14 -> 228
    //   217: aload_0
    //   218: getfield 14	com/tencent/mm/at/e:iHF	Lcom/tencent/mm/at/d;
    //   221: iload 7
    //   223: aload 16
    //   225: invokevirtual 144	com/tencent/mm/at/d:B	(ILjava/lang/String;)V
    //   228: aload_0
    //   229: getfield 14	com/tencent/mm/at/e:iHF	Lcom/tencent/mm/at/d;
    //   232: invokestatic 45	com/tencent/mm/at/d:b	(Lcom/tencent/mm/at/d;)Z
    //   235: pop
    //   236: return
    //   237: astore 5
    //   239: ldc 146
    //   241: aload 5
    //   243: ldc 148
    //   245: iconst_0
    //   246: anewarray 4	java/lang/Object
    //   249: invokestatic 152	com/tencent/mm/sdk/platformtools/z:printErrStackTrace	(Ljava/lang/String;Ljava/lang/Throwable;Ljava/lang/String;[Ljava/lang/Object;)V
    //   252: new 22	java/lang/IncompatibleClassChangeError
    //   255: dup
    //   256: ldc 148
    //   258: invokespecial 153	java/lang/IncompatibleClassChangeError:<init>	(Ljava/lang/String;)V
    //   261: aload 5
    //   263: invokevirtual 157	java/lang/IncompatibleClassChangeError:initCause	(Ljava/lang/Throwable;)Ljava/lang/Throwable;
    //   266: checkcast 22	java/lang/IncompatibleClassChangeError
    //   269: athrow
    //   270: astore_3
    //   271: aload_0
    //   272: getfield 14	com/tencent/mm/at/e:iHF	Lcom/tencent/mm/at/d;
    //   275: invokestatic 45	com/tencent/mm/at/d:b	(Lcom/tencent/mm/at/d;)Z
    //   278: pop
    //   279: aload_3
    //   280: athrow
    //   281: astore_1
    //   282: ldc 89
    //   284: aload_1
    //   285: ldc 159
    //   287: iconst_0
    //   288: anewarray 4	java/lang/Object
    //   291: invokestatic 152	com/tencent/mm/sdk/platformtools/z:printErrStackTrace	(Ljava/lang/String;Ljava/lang/Throwable;Ljava/lang/String;[Ljava/lang/Object;)V
    //   294: aload_0
    //   295: getfield 14	com/tencent/mm/at/e:iHF	Lcom/tencent/mm/at/d;
    //   298: invokestatic 45	com/tencent/mm/at/d:b	(Lcom/tencent/mm/at/d;)Z
    //   301: pop
    //   302: return
    //
    // Exception table:
    //   from	to	target	type
    //   0	30	237	java/lang/IncompatibleClassChangeError
    //   44	165	237	java/lang/IncompatibleClassChangeError
    //   174	197	237	java/lang/IncompatibleClassChangeError
    //   197	228	237	java/lang/IncompatibleClassChangeError
    //   0	30	270	finally
    //   44	165	270	finally
    //   174	197	270	finally
    //   197	228	270	finally
    //   239	270	270	finally
    //   282	294	270	finally
    //   0	30	281	java/lang/Throwable
    //   44	165	281	java/lang/Throwable
    //   174	197	281	java/lang/Throwable
    //   197	228	281	java/lang/Throwable
  }
}

/* Location:           /Users/zhouji/projects/wechat-android-study/classes_dex2jar.jar
 * Qualified Name:     com.tencent.mm.at.e
 * JD-Core Version:    0.6.2
 */