package com.tencent.mm.app;

final class d
  implements Runnable
{
  d(c paramc)
  {
  }

  // ERROR //
  public final void run()
  {
    // Byte code:
    //   0: ldc 20
    //   2: ldc 22
    //   4: invokestatic 28	com/tencent/mm/sdk/platformtools/z:e	(Ljava/lang/String;Ljava/lang/String;)V
    //   7: invokestatic 34	com/tencent/mm/sdk/platformtools/ak:getContext	()Landroid/content/Context;
    //   10: astore_1
    //   11: new 36	android/content/Intent
    //   14: dup
    //   15: aload_1
    //   16: ldc 38
    //   18: invokespecial 41	android/content/Intent:<init>	(Landroid/content/Context;Ljava/lang/Class;)V
    //   21: astore_2
    //   22: ldc 20
    //   24: ldc 43
    //   26: invokestatic 46	com/tencent/mm/sdk/platformtools/z:i	(Ljava/lang/String;Ljava/lang/String;)V
    //   29: aload_1
    //   30: aload_0
    //   31: getfield 12	com/tencent/mm/app/d:cFN	Lcom/tencent/mm/app/c;
    //   34: invokevirtual 52	android/content/Context:unbindService	(Landroid/content/ServiceConnection;)V
    //   37: aload_1
    //   38: aload_2
    //   39: invokevirtual 56	android/content/Context:stopService	(Landroid/content/Intent;)Z
    //   42: pop
    //   43: aload_1
    //   44: aload_2
    //   45: aload_0
    //   46: getfield 12	com/tencent/mm/app/d:cFN	Lcom/tencent/mm/app/c;
    //   49: iconst_1
    //   50: invokevirtual 60	android/content/Context:bindService	(Landroid/content/Intent;Landroid/content/ServiceConnection;I)Z
    //   53: pop
    //   54: return
    //   55: astore 6
    //   57: aload_1
    //   58: aload_2
    //   59: invokevirtual 56	android/content/Context:stopService	(Landroid/content/Intent;)Z
    //   62: pop
    //   63: aload_1
    //   64: aload_2
    //   65: aload_0
    //   66: getfield 12	com/tencent/mm/app/d:cFN	Lcom/tencent/mm/app/c;
    //   69: iconst_1
    //   70: invokevirtual 60	android/content/Context:bindService	(Landroid/content/Intent;Landroid/content/ServiceConnection;I)Z
    //   73: pop
    //   74: return
    //   75: astore_3
    //   76: aload_1
    //   77: aload_2
    //   78: invokevirtual 56	android/content/Context:stopService	(Landroid/content/Intent;)Z
    //   81: pop
    //   82: aload_1
    //   83: aload_2
    //   84: aload_0
    //   85: getfield 12	com/tencent/mm/app/d:cFN	Lcom/tencent/mm/app/c;
    //   88: iconst_1
    //   89: invokevirtual 60	android/content/Context:bindService	(Landroid/content/Intent;Landroid/content/ServiceConnection;I)Z
    //   92: pop
    //   93: aload_3
    //   94: athrow
    //
    // Exception table:
    //   from	to	target	type
    //   22	37	55	java/lang/Exception
    //   22	37	75	finally
  }
}

/* Location:           /Users/zhouji/projects/wechat-android-study/classes_dex2jar.jar
 * Qualified Name:     com.tencent.mm.app.d
 * JD-Core Version:    0.6.2
 */